{"id":"5249","title":"Dolcino To Margaret","author":"Charles Kingsley","copyright":null,"content":"The world goes up and the world goes down,\nAnd the sunshine follows the rain;\nAnd yesterday's sneer and yesterday's frown\nCan never come over again,\nSweet wife:\nNo, never come over again.\n\nFor woman is warm though man be cold,\nAnd the night will hallow the day;\nTill the heart which at even was weary and old\nCan rise in the morning gay,\nSweet wife;\nTo its work in the morning gay.\n\nAndernach, 1851. \n\t\t\t\t\t\t\n","url":"https://www.poetry.net/poem/5249/dolcino-to-margaret"}